{
  "relatives": {
    "-1": "الربع الأخير",
    "0": "هذا الربع",
    "1": "الربع القادم"
  },
  "past": {
    "one": [
      0,
      "قبل ربع سنة واحد"
    ],
    "two": [
      0,
      "قبل ربعي سنة"
    ],
    "few": [
      0,
      "قبل {0} أرباع سنة"
    ],
    "other": [
      0,
      "قبل {0} ربع سنة"
    ]
  },
  "future": {
    "one": [
      0,
      "خلال ربع سنة واحد"
    ],
    "two": [
      0,
      "خلال ربعي سنة"
    ],
    "few": [
      0,
      "خلال {0} أرباع سنة"
    ],
    "other": [
      0,
      "خلال {0} ربع سنة"
    ]
  }
}
