{
  "defaults": {
    "3": "Orta Afrika Saati",
    "4": "Doğu Afrika Saati",
    "5": "Güney Afrika Standart Saati",
    "33": "Brunei Darü’s-Selam Saati",
    "36": "Chamorro Saati",
    "41": "Cocos Adaları Saati",
    "47": "Doğu Timor Saati",
    "57": "Fransız Güney ve Antarktika Saati",
    "58": "Greenwich Ortalama Saati",
    "62": "Gilbert Adaları Saati",
    "67": "Körfez Saati",
    "72": "Hindistan Standart Saati",
    "73": "Hint Okyanusu Saati",
    "74": "Hindiçin Saati",
    "75": "Orta Endonezya Saati",
    "76": "Doğu Endonezya Saati",
    "77": "Batı Endonezya Saati",
    "83": "Kazakistan Saati",
    "84": "Doğu Kazakistan Saati",
    "85": "Batı Kazakistan Saati",
    "91": "Line Adaları Saati",
    "95": "Malezya Saati",
    "98": "Marshall Adaları Saati",
    "104": "Myanmar Saati",
    "118": "Papua Yeni Gine Saati",
    "122": "Phoenix Adaları Saati",
    "124": "Pitcairn Saati",
    "125": "Ponape Saati",
    "126": "Pyongyang Saati",
    "134": "Singapur Standart Saati",
    "136": "Güney Georgia Saati",
    "154": "Wake Adası Saati",
    "158": "Yukon Saati"
  },
  "overrides": {
    "utc": "Eş Güdümlü Evrensel Zaman"
  }
}
