{
  "relatives": {
    "-1": "الربع الأخير",
    "0": "هذا الربع",
    "1": "الربع القادم"
  },
  "past": {
    "one": [
      0,
      [
        {
          "Literal": "قبل ربع سنة واحد"
        }
      ]
    ],
    "two": [
      0,
      [
        {
          "Literal": "قبل ربعي سنة"
        }
      ]
    ],
    "few": [
      0,
      [
        {
          "Literal": "قبل "
        },
        {
          "Placeholder": "Singleton"
        },
        {
          "Literal": " أرباع سنة"
        }
      ]
    ],
    "other": [
      0,
      [
        {
          "Literal": "قبل "
        },
        {
          "Placeholder": "Singleton"
        },
        {
          "Literal": " ربع سنة"
        }
      ]
    ]
  },
  "future": {
    "one": [
      0,
      [
        {
          "Literal": "خلال ربع سنة واحد"
        }
      ]
    ],
    "two": [
      0,
      [
        {
          "Literal": "خلال ربعي سنة"
        }
      ]
    ],
    "few": [
      0,
      [
        {
          "Literal": "خلال "
        },
        {
          "Placeholder": "Singleton"
        },
        {
          "Literal": " أرباع سنة"
        }
      ]
    ],
    "other": [
      0,
      [
        {
          "Literal": "خلال "
        },
        {
          "Placeholder": "Singleton"
        },
        {
          "Literal": " ربع سنة"
        }
      ]
    ]
  }
}
