{
  "relatives": {
    "-1": "ğ‘„‰ğ‘„¬ğ‘„£ğ‘„³ğ‘„ ğ‘„¬ ğ‘„–ğ‘„¨ğ‘„šğ‘„´ğ‘„Ÿğ‘„ğ‘„§ğ‘„¢ğ‘„´",
    "0": "ğ‘„ƒğ‘„³ğ‘„†ğ‘„¬ ğ‘„–ğ‘„¨ğ‘„šğ‘„´ğ‘„Ÿğ‘„ğ‘„§ğ‘„¢ğ‘„´",
    "1": "ğ‘„›ğ‘„§ğ‘„¢ğ‘„¬ ğ‘„–ğ‘„¨ğ‘„šğ‘„´ğ‘„Ÿğ‘„ğ‘„§ğ‘„¢ğ‘„´"
  },
  "past": {
    "other": [
      0,
      [
        {
          "Placeholder": "Singleton"
        },
        {
          "Literal": "ğ‘„–ğ‘„¨ğ‘„šğ‘„´ğ‘„Ÿğ‘„ğ‘„§ğ‘„¢ğ‘„´ ğ‘„ƒğ‘„‰ğ‘„¬"
        }
      ]
    ]
  },
  "future": {
    "other": [
      0,
      [
        {
          "Placeholder": "Singleton"
        },
        {
          "Literal": " ğ‘„–ğ‘„¨ğ‘„šğ‘„´ğ‘„Ÿğ‘„ğ‘„¬"
        }
      ]
    ]
  }
}
