{
  "relatives": {
    "-2": "أول أمس",
    "-1": "أمس",
    "0": "اليوم",
    "1": "غدًا",
    "2": "بعد الغد"
  },
  "past": {
    "one": [
      0,
      [
        {
          "Literal": "قبل يوم واحد"
        }
      ]
    ],
    "two": [
      0,
      [
        {
          "Literal": "قبل يومين"
        }
      ]
    ],
    "few": [
      0,
      [
        {
          "Literal": "قبل "
        },
        {
          "Placeholder": "Singleton"
        },
        {
          "Literal": " أيام"
        }
      ]
    ],
    "many": [
      0,
      [
        {
          "Literal": "قبل "
        },
        {
          "Placeholder": "Singleton"
        },
        {
          "Literal": " يومًا"
        }
      ]
    ],
    "other": [
      0,
      [
        {
          "Literal": "قبل "
        },
        {
          "Placeholder": "Singleton"
        },
        {
          "Literal": " يوم"
        }
      ]
    ]
  },
  "future": {
    "one": [
      0,
      [
        {
          "Literal": "خلال يوم واحد"
        }
      ]
    ],
    "two": [
      0,
      [
        {
          "Literal": "خلال يومين"
        }
      ]
    ],
    "few": [
      0,
      [
        {
          "Literal": "خلال "
        },
        {
          "Placeholder": "Singleton"
        },
        {
          "Literal": " أيام"
        }
      ]
    ],
    "many": [
      0,
      [
        {
          "Literal": "خلال "
        },
        {
          "Placeholder": "Singleton"
        },
        {
          "Literal": " يومًا"
        }
      ]
    ],
    "other": [
      0,
      [
        {
          "Literal": "خلال "
        },
        {
          "Placeholder": "Singleton"
        },
        {
          "Literal": " يوم"
        }
      ]
    ]
  }
}
