{
  "relatives": {
    "0": "este minuto"
  },
  "past": {
    "one": [
      0,
      [
        {
          "Literal": "hace "
        },
        {
          "Placeholder": "Singleton"
        },
        {
          "Literal": " minuto"
        }
      ]
    ],
    "other": [
      0,
      [
        {
          "Literal": "hace "
        },
        {
          "Placeholder": "Singleton"
        },
        {
          "Literal": " minutos"
        }
      ]
    ]
  },
  "future": {
    "one": [
      0,
      [
        {
          "Literal": "dentro de "
        },
        {
          "Placeholder": "Singleton"
        },
        {
          "Literal": " minuto"
        }
      ]
    ],
    "other": [
      0,
      [
        {
          "Literal": "dentro de "
        },
        {
          "Placeholder": "Singleton"
        },
        {
          "Literal": " minutos"
        }
      ]
    ]
  }
}
