{
  "locations": {
    "bjptn": "Bénin",
    "cfbgf": "République centrafricaine",
    "cgbzv": "Congo-Brazzaville",
    "cmdla": "Cameroun",
    "dosdq": "República Dominicana",
    "dzalg": "Algérie",
    "esmad": "España",
    "gfcay": "Guyane française",
    "gncky": "Guinée",
    "gpmsb": "Saint-Martin",
    "gpsbh": "Saint-Barthélemy",
    "gqssg": "Guinea Ecuatorial",
    "kmyva": "Comores",
    "kzksn": "Qostanay",
    "macas": "Maroc",
    "metgd": "Crna Gora",
    "mrnkc": "Mauritanie",
    "ncnou": "Nouvelle-Calédonie",
    "papty": "Panamá",
    "pelim": "Perú",
    "phmnl": "Pilipinas",
    "pmmqc": "Saint-Pierre-et-Miquelon",
    "rereu": "La Réunion",
    "rsbeg": "Srbija",
    "sndkr": "Sénégal",
    "sydam": "Syrie",
    "tdndj": "Tchad",
    "tfpfr": "Terres australes françaises",
    "tntun": "Tunisie",
    "wfmau": "Wallis-et-Futuna"
  },
  "pattern_generic": [
    {
      "Placeholder": "Singleton"
    }
  ],
  "pattern_standard": [
    {
      "Placeholder": "Singleton"
    },
    {
      "Literal": " (+0)"
    }
  ],
  "pattern_daylight": [
    {
      "Placeholder": "Singleton"
    },
    {
      "Literal": " (+1)"
    }
  ],
  "pattern_partial_location": [
    {
      "Placeholder": "Place1"
    },
    {
      "Literal": " ("
    },
    {
      "Placeholder": "Place0"
    },
    {
      "Literal": ")"
    }
  ]
}
